acurl_ng.cpython-39-darwin.so
acurl_ng-0.1.dist-info/METADATA
acurl_ng-0.1.dist-info/WHEEL
acurl_ng-0.1.dist-info/top_level.txt
acurl_ng-0.1.dist-info/RECORD
