Metadata-Version: 2.1
Name: acurl-ng
Version: 0.1
Summary: An async Curl library.
Home-page: https://github.com/sky-uk/mite/tree/master/acurl_ng
Author: Aaron Ecay
Author-email: aaron.ecay@sky.uk
Maintainer: Sky Identity NFT team
Maintainer-email: matthew.ellis@sky.uk
License: MIT
Classifier: Development Status :: 3 - Alpha
Classifier: Intended Audience :: Developers
Classifier: Programming Language :: Python
Classifier: Programming Language :: Python :: 3
Classifier: Programming Language :: Python :: 3.9
Requires-Dist: ujson (>=4.1.0)
Requires-Dist: uvloop
